fastinference/FastInference.py
fastinference/__init__.py
fastinference_llm-0.1.dist-info/LICENSE.txt
fastinference_llm-0.1.dist-info/METADATA
fastinference_llm-0.1.dist-info/WHEEL
fastinference_llm-0.1.dist-info/top_level.txt
fastinference_llm-0.1.dist-info/RECORD
