Metadata-Version: 2.1
Name: fastinference-llm
Version: 0.1
Summary: Seamlessly integrate with top LLM APIs for speedy, robust, and scalable querying. Ideal for developers needing quick, reliable AI-powered responses.
Home-page: https://github.com/blefo/FastInference
Download-URL: https://github.com/blefo/FastInference/archive/v_01.tar.gz
Author: Baptiste Lefort
Author-email: lefort.baptiste@icloud.com
License: MIT
Keywords: api,fast,inference,distributed,llm
Classifier: Development Status :: 3 - Alpha
Classifier: Intended Audience :: Developers
Classifier: Topic :: Software Development :: Build Tools
Classifier: License :: OSI Approved :: MIT License
Classifier: Programming Language :: Python :: 3
Classifier: Programming Language :: Python :: 3.4
Classifier: Programming Language :: Python :: 3.5
Classifier: Programming Language :: Python :: 3.6
License-File: LICENSE.txt
Requires-Dist: validators
Requires-Dist: beautifulsoup4
